friendlier_json/__init__.py
friendlier_json/transactions.py
friendlier_json-0.0.1.1.dist-info/LICENSE
friendlier_json-0.0.1.1.dist-info/METADATA
friendlier_json-0.0.1.1.dist-info/WHEEL
friendlier_json-0.0.1.1.dist-info/top_level.txt
friendlier_json-0.0.1.1.dist-info/RECORD
