Metadata-Version: 2.1
Name: friendlier-json
Version: 0.0.1.1
Summary: A small package that turns a .json into a database !
Home-page: https://github.com/py-alpha-woelfchen/friendlier-json
Author: Leo Breuer
License: UNKNOWN
Platform: UNKNOWN
Classifier: Programming Language :: Python :: 3
Classifier: License :: OSI Approved :: MIT License
Classifier: Operating System :: OS Independent
Requires-Python: >=3.5
